setup.cfg
setup.py
ptrans.egg-info/PKG-INFO
ptrans.egg-info/SOURCES.txt
ptrans.egg-info/dependency_links.txt
ptrans.egg-info/entry_points.txt
ptrans.egg-info/requires.txt
ptrans.egg-info/top_level.txt
ptrans.egg-info/zip-safe
trans/__init__.py
trans/config.py
trans/translate.py