Metadata-Version: 1.1
Name: ptrans
Version: 0.3.2
Summary: A command line tool help you trans other lauguages to Chinese each other
Home-page: https://github.com/linrz/trans-tool
Author: linrz
Author-email: 1246533834@qq.com
License: MIT
Keywords: trans terminal
Platform: UNKNOWN
Classifier: Programming Language :: Python
Classifier: Programming Language :: Python :: 3.5
